mksolutions/__init__.py
mksolutions/__version__.py
mksolutions/_base_client.py
mksolutions/_client.py
mksolutions/_constants.py
mksolutions/_exceptions.py
mksolutions/_models.py
mksolutions/_qs.py
mksolutions/_resource.py
mksolutions/_types.py
mksolutions/_utils/__init__.py
mksolutions/_utils/_logs.py
mksolutions/_utils/_utils.py
mksolutions/resources/__init__.py
mksolutions/resources/auths.py
mksolutions/resources/clients.py
mksolutions/resources/connections.py
mksolutions/resources/contracts.py
mksolutions/types/__init__.py
mksolutions/types/auths.py
mksolutions/types/clients_by_doc.py
mksolutions/types/clients_by_doc_response.py
mksolutions/types/clients_find_by_doc_params.py
mksolutions/types/connections_by_client_id.py
mksolutions/types/connections_by_client_id_response.py
mksolutions/types/connections_find_by_client_id_params.py
mksolutions-0.8.5.dist-info/METADATA
mksolutions-0.8.5.dist-info/WHEEL
mksolutions-0.8.5.dist-info/licenses/LICENSE
mksolutions-0.8.5.dist-info/RECORD
