Metadata-Version: 2.3
Name: mksolutions
Version: 0.8.5
Summary: The community Python library for the MK Solutions ERP API
Project-URL: Homepage, https://github.com/DevDeividMoura/mksolutions-api-py
Project-URL: Repository, https://github.com/DevDeividMoura/mksolutions-api-py
Author-email: Deivid Carvalho Moura <deividcarvalhomoura@gmail.com>
License-Expression: MIT
License-File: LICENSE
Classifier: Intended Audience :: Developers
Classifier: License :: OSI Approved :: MIT License
Classifier: Operating System :: MacOS
Classifier: Operating System :: Microsoft :: Windows
Classifier: Operating System :: OS Independent
Classifier: Operating System :: POSIX
Classifier: Operating System :: POSIX :: Linux
Classifier: Programming Language :: Python :: 3.8
Classifier: Programming Language :: Python :: 3.9
Classifier: Programming Language :: Python :: 3.10
Classifier: Programming Language :: Python :: 3.11
Classifier: Programming Language :: Python :: 3.12
Classifier: Topic :: Software Development :: Libraries :: Python Modules
Classifier: Typing :: Typed
Requires-Python: >=3.8
Requires-Dist: annotated-types==0.7.0
Requires-Dist: anyio==4.4.0
Requires-Dist: beautifulsoup4==4.12.3
Requires-Dist: bs4==0.0.2
Requires-Dist: certifi==2024.6.2
Requires-Dist: h11==0.14.0
Requires-Dist: httpcore==1.0.5
Requires-Dist: httpx==0.27.0
Requires-Dist: idna==3.7
Requires-Dist: iniconfig==2.0.0
Requires-Dist: packaging==24.1
Requires-Dist: pluggy==1.5.0
Requires-Dist: pydantic-core==2.18.4
Requires-Dist: pydantic==2.7.4
Requires-Dist: python-dotenv==1.0.1
Requires-Dist: sniffio==1.3.1
Requires-Dist: soupsieve==2.5
Requires-Dist: typing-extensions==4.12.2
